pysprite/__init__.py
pysprite/spritesheet.py
pysprite_lib-0.1.3.dist-info/METADATA
pysprite_lib-0.1.3.dist-info/WHEEL
pysprite_lib-0.1.3.dist-info/top_level.txt
pysprite_lib-0.1.3.dist-info/RECORD
