Metadata-Version: 2.1
Name: pysprite_lib
Version: 0.1.3
Summary: pygame spritesheet simplifier
Home-page: https://github.com/QZ-K/pysprite_lib
Author: QZ
Author-email: kuzeykural040510@gmail.com
Classifier: Programming Language :: Python :: 3
Classifier: License :: OSI Approved :: MIT License
Classifier: Operating System :: OS Independent
Requires-Python: >=3.6
Requires-Dist: pygame
